utilitarian_queue_consumer/__init__.py
utilitarian_queue_consumer/management.py
utilitarian_queue_consumer/workers.py
utilitarian_queue_consumer/conf/__init__.py
utilitarian_queue_consumer/conf/global_settings.py
utilitarian_queue_consumer/utils/__init__.py
utilitarian_queue_consumer/utils/log.py
utilitarian_queue_consumer/utils/module_loading.py
utilitarian_queue_consumer-0.0.6.dist-info/LICENSE.txt
utilitarian_queue_consumer-0.0.6.dist-info/METADATA
utilitarian_queue_consumer-0.0.6.dist-info/RECORD
utilitarian_queue_consumer-0.0.6.dist-info/WHEEL
utilitarian_queue_consumer-0.0.6.dist-info/top_level.txt
